ideplots/__init__.py
ideplots/styles/vscode/vscode-dark-modern.mplstyle
ideplots-0.1.1.dist-info/LICENSE
ideplots-0.1.1.dist-info/METADATA
ideplots-0.1.1.dist-info/WHEEL
ideplots-0.1.1.dist-info/top_level.txt
ideplots-0.1.1.dist-info/RECORD
