Metadata-Version: 2.1
Name: ideplots
Version: 0.1.1
Summary: Format Matplotlib for easy viewing in IDEs
Home-page: https://github.com/benabernathy/ideplots/
Author: Ben Abernathy
Author-email: ben.abernathy@gmail.com
Maintainer: Ben Abernathy
Maintainer-email: ben.abernathy@gmail.com
License: MIT
Keywords: matplotlib-style-sheets,matplotlib-figures,matplotlib-styles,python
Classifier: Framework :: Matplotlib
Classifier: License :: OSI Approved :: MIT License
Classifier: Programming Language :: Python :: 3
License-File: LICENSE
Requires-Dist: matplotlib
